tjess/__init__.py
tjess/agent/__init__.py
tjess/agent/agent.py
tjess/agent/decorators.py
tjess/agent/manifest.py
tjess/agent/runner.py
tjess/agent/clients/__init__.py
tjess/agent/clients/air.py
tjess/agent/clients/identity.py
tjess/agent/node/__init__.py
tjess/agent/node/message_queue.py
tjess/agent/node/publisher.py
tjess/agent/node/rate.py
tjess/agent/node/service.py
tjess/agent/node/subscriber.py
tjess/agent/node/task.py
tjess/agent/node/tjess_node.py
tjess/cli/__init__.py
tjess/cli/config.py
tjess/cli/main.py
tjess/cli/commands/__init__.py
tjess/cli/commands/agent.py
tjess/cli/commands/auth.py
tjess/cli/commands/init.py
tjess-0.1.0.dist-info/METADATA
tjess-0.1.0.dist-info/WHEEL
tjess-0.1.0.dist-info/entry_points.txt
tjess-0.1.0.dist-info/RECORD
